ytsnippet/__init__.py
ytsnippet/cli.py
ytsnippet/database.py
ytsnippet-0.4.dist-info/METADATA
ytsnippet-0.4.dist-info/WHEEL
ytsnippet-0.4.dist-info/entry_points.txt
ytsnippet-0.4.dist-info/top_level.txt
ytsnippet-0.4.dist-info/RECORD
