Metadata-Version: 2.1
Name: ytsnippet
Version: 0.4
Summary: A simple code snippet manager
Home-page: https://github.com/2222038
Author: Yokoyama Takumi
Author-email: s2222038@stu.musashino-u.ac.jp
Classifier: Programming Language :: Python :: 3
Classifier: License :: OSI Approved :: MIT License
Classifier: Operating System :: OS Independent
Requires-Python: >=3.6
Requires-Dist: prompt-toolkit
